invenio_opendefinition/__init__.py
invenio_opendefinition/cli.py
invenio_opendefinition/config.py
invenio_opendefinition/ext.py
invenio_opendefinition/fetchers.py
invenio_opendefinition/indexer.py
invenio_opendefinition/loaders.py
invenio_opendefinition/minters.py
invenio_opendefinition/proxies.py
invenio_opendefinition/resolvers.py
invenio_opendefinition/tasks.py
invenio_opendefinition/utils.py
invenio_opendefinition/validators.py
invenio_opendefinition/version.py
invenio_opendefinition/jsonschemas/__init__.py
invenio_opendefinition/jsonschemas/licenses/license-v1.0.0.json
invenio_opendefinition/mappings/__init__.py
invenio_opendefinition/mappings/licenses/license-v1.0.0.json
invenio_opendefinition/mappings/os-v1/__init__.py
invenio_opendefinition/mappings/os-v1/licenses/license-v1.0.0.json
invenio_opendefinition/mappings/os-v2/__init__.py
invenio_opendefinition/mappings/os-v2/licenses/license-v1.0.0.json
invenio_opendefinition/mappings/v5/__init__.py
invenio_opendefinition/mappings/v5/licenses/license-v1.0.0.json
invenio_opendefinition/mappings/v6/__init__.py
invenio_opendefinition/mappings/v6/licenses/license-v1.0.0.json
invenio_opendefinition/mappings/v7/__init__.py
invenio_opendefinition/mappings/v7/licenses/license-v1.0.0.json
invenio_opendefinition-2.0.0a2.dist-info/AUTHORS.rst
invenio_opendefinition-2.0.0a2.dist-info/LICENSE
invenio_opendefinition-2.0.0a2.dist-info/METADATA
invenio_opendefinition-2.0.0a2.dist-info/WHEEL
invenio_opendefinition-2.0.0a2.dist-info/entry_points.txt
invenio_opendefinition-2.0.0a2.dist-info/top_level.txt
invenio_opendefinition-2.0.0a2.dist-info/RECORD
