Metadata-Version: 2.1
Name: invenio-opendefinition
Version: 2.0.0a2
Summary: Invenio module integrating Invenio repositories and OpenDefinition.
Home-page: https://github.com/inveniosoftware/invenio-opendefinition
Author: CERN
Author-email: info@inveniosoftware.org
License: MIT
Keywords: invenio TODO
Platform: any
Classifier: Environment :: Web Environment
Classifier: Intended Audience :: Developers
Classifier: License :: OSI Approved :: MIT License
Classifier: Operating System :: OS Independent
Classifier: Programming Language :: Python
Classifier: Topic :: Internet :: WWW/HTTP :: Dynamic Content
Classifier: Topic :: Software Development :: Libraries :: Python Modules
Classifier: Programming Language :: Python :: 2
Classifier: Programming Language :: Python :: 2.7
Classifier: Programming Language :: Python :: 3
Classifier: Programming Language :: Python :: 3.5
Classifier: Programming Language :: Python :: Implementation :: CPython
Classifier: Development Status :: 5 - Production/Stable
Requires-Dist: Flask >=1.0.4
Requires-Dist: click >=7.0
Requires-Dist: invenio-i18n >=2.0.0
Requires-Dist: invenio-indexer >=2.0.0
Requires-Dist: invenio-jsonschemas >=1.0.0
Requires-Dist: invenio-pidstore >=1.0.0
Requires-Dist: invenio-records >=1.0.0
Requires-Dist: invenio-records-rest >=2.2.0
Requires-Dist: jsonref >=0.1
Requires-Dist: jsonresolver >=0.2.1
Requires-Dist: jsonschema >=2.5.1
Requires-Dist: requests >=2.9.1
Provides-Extra: docs
Requires-Dist: Sphinx >=5.0.0 ; extra == 'docs'
Provides-Extra: elasticsearch7
Requires-Dist: invenio-search[elasticsearch7] <3.0.0,>=2.0.0 ; extra == 'elasticsearch7'
Requires-Dist: elasticsearch <7.14,>=7.0.0 ; extra == 'elasticsearch7'
Provides-Extra: opensearch1
Requires-Dist: invenio-search[opensearch1] >=2.0.0 ; extra == 'opensearch1'
Provides-Extra: opensearch2
Requires-Dist: invenio-search[opensearch2] >=2.0.0 ; extra == 'opensearch2'
Provides-Extra: tests
Requires-Dist: httpretty >=1.0.3 ; extra == 'tests'
Requires-Dist: pytest-black <0.3.10,>=0.3.0 ; extra == 'tests'
Requires-Dist: pytest-invenio >=1.4.0 ; extra == 'tests'
Requires-Dist: invenio-db[versioning] >=1.0.14 ; extra == 'tests'
Requires-Dist: Sphinx >=5.0.0 ; extra == 'tests'
